main.py
talu-0.0.0.dist-info/METADATA
talu-0.0.0.dist-info/WHEEL
talu-0.0.0.dist-info/top_level.txt
talu-0.0.0.dist-info/RECORD
