Metadata-Version: 2.4
Name: talu
Version: 0.0.0
Summary: Talu
Requires-Python: >=3.10
